mux2/mux2.v
`timescale 1ns / 1ps

module mux2 #(parameter WLOG = 5) (a, sel, out, out_neg);
	
	//procedural block and continuous assignment
	//parameter WLOG = 6;
	//parameter WGLOBAL = (2 << WLOG);

	input [(1<<WLOG)-1:0] a;
	input [WLOG-1:0] sel;
	output reg out;
	output wire out_neg;
	
	always@(*)	begin
		out = a[sel];
	end

	assign out_neg=~out;


endmodule

mux2/tb_mux2.v
`timescale 1ns / 1ps

`define	PARAMLOG 3

module tb_mux2();

	reg clk;
	reg [(1 << `PARAMLOG)-1:0] a;
	reg [`PARAMLOG-1:0] sel;
	wire out, out_neg;

	mux2 #(.WLOG(`PARAMLOG))	
		dut(.a(a), .sel(sel), .out(out), .out_neg(out_neg));

	initial	begin
		$dumpfile("mux2_test.vcd");
		$dumpvars(0,tb_mux2);

		a=0; clk=0; sel=0;
		$monitor("Time = %0d clk=%d f(A-%b, S-%b)->(%d,%d)",$time, clk, a, sel, out, out_neg);
		//$dumpfile("mux2_test.vcd");
		//$dumpvars(0,tb_mux2);
		#1; a=0;sel=3;
		#1; a=1;sel=3;
		#1; a=2;sel=3;
		#1; a=3;sel=3;
		#1; a=4;sel=3;
		#1; a=5;sel=3;
		#1; a=6;sel=3;
		#1; a=7;sel=3;
		#1; a=8;sel=3;
		#1; a=9;sel=3;
		#1; a=10;sel=3;
		#1; a=11;sel=3;
		#1; a=12;sel=3;
		#1; a=13;sel=3;
		#1; a=14;sel=3;
		#1; a=15;sel=3;
		#1; a=16;sel=3;
		#20;
		$finish;
	end

	always	begin
		#5 clk = ~clk;
	end


endmodule

mux2/mux2_test.vcd
$date
	Fri Feb  6 22:09:02 2026
$end
$version
	Icarus Verilog
$end
$timescale
	1ps
$end
$scope module tb_mux2 $end
$var wire 1 ! out_neg $end
$var wire 1 " out $end
$var reg 8 # a [7:0] $end
$var reg 1 $ clk $end
$var reg 3 % sel [2:0] $end
$scope module dut $end
$var wire 8 & a [7:0] $end
$var wire 1 ! out_neg $end
$var wire 3 ' sel [2:0] $end
$var parameter 32 ( WLOG $end
$var reg 1 " out $end
$upscope $end
$upscope $end
$enddefinitions $end
$comment Show the parameter values. $end
$dumpall
b11 (
$end
#0
$dumpvars
b0 '
b0 &
b0 %
0$
b0 #
0"
1!
$end
#1000
b11 %
b11 '
#2000
b1 #
b1 &
#3000
b10 #
b10 &
#4000
b11 #
b11 &
#5000
b100 #
b100 &
1$
#6000
b101 #
b101 &
#7000
b110 #
b110 &
#8000
b111 #
b111 &
#9000
0!
1"
b1000 #
b1000 &
#10000
b1001 #
b1001 &
0$
#11000
b1010 #
b1010 &
#12000
b1011 #
b1011 &
#13000
b1100 #
b1100 &
#14000
b1101 #
b1101 &
#15000
b1110 #
b1110 &
1$
#16000
b1111 #
b1111 &
#17000
1!
0"
b10000 #
b10000 &
