mux1/mux1.v
`timescale 1ns / 1ns

module mux1(a, b, sel, out, out_neg);
input wire a, b, sel;
/*
	//dataflow design-style
	output wire out, out_neg;
	assign out = sel ? a : b;	//continuous assignment, left wire, right wire/reg
	assign out_neg = ~out;
*/
	
	// gate-level design-style
	output wire out, out_neg;
	wire out1, out2, selb;
	and a1 (out1, a, sel);
	not i1 (selb, sel);
	and a2 (out2, b , selb);
	or o1 (out, out1, out2);
	assign out_neg = ~out;

/*
	//behavioural
	output reg out;
	output out_neg;		//treated as reg
	//procedural design-style (note the absence of a complete list of inputs!!!)
	always@(*)
	begin
	if (sel) 
		out = a;
	else 
		out = b;
	end
	assign out_neg = ~out;
	//procedural block and continuous assignment evaluated in parallel,
	//but assignment evaluated second due to constraints
*/

endmodule

mux1/tb_mux1.v
`timescale 1ns / 1ns

module tb_mux1();
	reg clk;
	reg a, b;
	reg sel;
	wire out, out_neg;
	// single mux 2_to_1 single bit
	mux1 dut( .a(a), .b(b), .sel(sel),
							.out(out), .out_neg(out_neg)
						);
	initial
	begin
		$dumpfile("mux1.vcd");
		$dumpvars(0,tb_mux1);
		a=0;b=0;sel=0;clk=0;
		$monitor ("Time = %0d clk=%d f(A-%d,B-%d,S-%d)->(%d,%d))",$time, clk,a,b,sel,out,out_neg);	
		#5; a=1;b=0;sel=0;
		#7; a=1;b=0;sel=1;
		#10; a=1;b=1;sel=0;
		#15; a=1;b=0;sel=1;
		#20; a=1;b=0;sel=0;
		#5; a=1;b=0;sel=1;
		// something subtle about synthesis and verification!!!! The X value, don't care for synthesis and unknown in simulation
		#5; a=1'bx;b=0;sel=1;
		#5; a=1'bx;b=0;sel=0;
		#5; a=1;b=0;sel=1'bx;
		#20;
		$finish;
	end
	
	always 
	begin
		#5 clk=~clk;
	end
endmodule

mux1/mux1.vcd
$date
	Fri Feb  6 18:01:06 2026
$end
$version
	Icarus Verilog
$end
$timescale
	1ns
$end
$scope module tb_mux1 $end
$var wire 1 ! out_neg $end
$var wire 1 " out $end
$var reg 1 # a $end
$var reg 1 $ b $end
$var reg 1 % clk $end
$var reg 1 & sel $end
$scope module dut $end
$var wire 1 # a $end
$var wire 1 $ b $end
$var wire 1 " out $end
$var wire 1 ' out1 $end
$var wire 1 ( out2 $end
$var wire 1 ! out_neg $end
$var wire 1 & sel $end
$var wire 1 ) selb $end
$upscope $end
$upscope $end
$enddefinitions $end
$comment Show the parameter values. $end
$dumpall
$end
#0
$dumpvars
1)
0(
0'
0&
0%
0$
0#
0"
1!
$end
#5
1%
1#
#10
0%
#12
0!
1"
1'
0)
1&
#15
1%
#20
0%
#22
1(
0'
1)
0&
1$
#25
1%
#30
0%
#35
1%
#37
1'
0)
0(
1&
0$
#40
0%
#45
1%
#50
0%
#55
1%
#57
1!
0"
0'
1)
0&
#60
0%
#62
0!
1"
1'
0)
1&
#65
1%
#67
x!
x"
x'
x#
#70
0%
#72
1!
0"
0'
1)
0&
#75
1%
#77
x!
x"
x)
x'
x&
1#
